{
  "description": "BTC-USDT · 1W/1D alcistas, 4H con pauta plana ABC retrocediendo a MM55+POC pero sin ruptura aún (última vela NO cierra sobre swing_high). Debe producir decision=wait y conditional_setups con watch_level = swing_high 4H.",
  "expected_decision": "wait",
  "expected_conditional_rule_ids": ["T003", "S001_invalidation"],
  "snapshot": {
    "symbol": "BTC-USDT",
    "as_of": 1776830400000,
    "flags": {"position_open": false},
    "portfolio": {"capital_usd": 15000},
    "timeframes": {
      "1W": {
        "timeframe": "1W",
        "bars": [],
        "indicators": {"mm55": 65000, "mm55_prev": 64500, "adx": 28.0, "adx_prev": 26.0}
      },
      "1D": {
        "timeframe": "1D",
        "bars": [],
        "indicators": {"mm55": 68000, "mm55_prev": 67600, "adx": 25.0, "adx_prev": 24.0}
      },
      "4H": {
        "timeframe": "4H",
        "bars_explanation": "Same ABC structure as enter_long, but the last bar does NOT break the swing_high; it closes at 71500 well below the swing_high ~74200.",
        "bars": [
          {"timestamp": 1776657600000, "open": 70000, "high": 71200, "low": 69900, "close": 71000, "volume": 1000},
          {"timestamp": 1776672000000, "open": 71000, "high": 72500, "low": 70800, "close": 72400, "volume": 1100},
          {"timestamp": 1776686400000, "open": 72400, "high": 74000, "low": 72200, "close": 73900, "volume": 1300},
          {"timestamp": 1776700800000, "open": 73900, "high": 74200, "low": 73100, "close": 73400, "volume": 900},
          {"timestamp": 1776715200000, "open": 73400, "high": 73600, "low": 71800, "close": 72000, "volume": 850},
          {"timestamp": 1776729600000, "open": 72000, "high": 72200, "low": 70600, "close": 70800, "volume": 1000},
          {"timestamp": 1776744000000, "open": 70800, "high": 71300, "low": 70500, "close": 70600, "volume": 800},
          {"timestamp": 1776758400000, "open": 70600, "high": 71400, "low": 70400, "close": 71300, "volume": 900},
          {"timestamp": 1776772800000, "open": 71300, "high": 72200, "low": 71100, "close": 72100, "volume": 950},
          {"timestamp": 1776787200000, "open": 72100, "high": 71900, "low": 71100, "close": 71500, "volume": 800}
        ],
        "indicators": {
          "mm55": 70500, "mm55_prev": 70400,
          "adx": 23.0, "adx_prev": 23.5,
          "poc": 71000, "vah": 74200, "val": 69000, "atr": 900, "volume_sma20": 1050
        }
      }
    }
  }
}
